Workbook

Sheet Matriz_Activos
A1: Matriz consolidada de activos por área y mantenimiento
A3: Cruce exacto de placas contra activos.xlsx. No se aplicaron correcciones automáticas a placas no coincidentes.
A4: Activo | B4: Nombre | C4: Descripción | D4: Área | E4: Dependencia | F4: Fecha de Último mantenimiento | G4: Orden Área | H4: Estado mantenimiento | I4: Aporta al Plan de Mejoramiento | J4: NUMERO_PERIODOS_VIDA_UTIL | K4: CANTIDAD_PERIODOS_DEPRECIADOS | L4: FECHA_INICIO_DEPRECIACION | M4: DEPRECIADO
A5: U15201000681 | B5: COMPACTADOR AUTOMÁTICO PARA ENSAYOS CBR Y PROCTOR | C5: EQUIPO LABORATORIO - COMPACTADOR AUTOMATICO PARA PROCTOR | D5: Académica | E5: CIPAV | G5: =IFERROR(VLOOKUP(D5,Listas!$A$2:$B$20,2,FALSE()),999) -> 1 | H5: =IF(F5="","Sin fecha",IF(TODAY()-F5>180,"Revisar",IF(TODAY()-F5>90,"Próximo","Vigente"))) -> Sin fecha | J5: 120 | K5: 8 | L5: 46023 | M5: N
A6: U15201000680 | B6: COMPACTADOR MARSHALL AUTOMÁTICO | C6: EQUIPO LABORATORIO - COMPACTADOR AUTOMATICO MARSHALL PARA MUESTRAS ASFALTICAS | D6: Académica | E6: CIPAV | G6: =IFERROR(VLOOKUP(D6,Listas!$A$2:$B$20,2,FALSE()),999) -> 1 | H6: =IF(F6="","Sin fecha",IF(TODAY()-F6>180,"Revisar",IF(TODAY()-F6>90,"Próximo","Vigente"))) -> Sin fecha | J6: 120 | K6: 8 | L6: 46023 | M6: N
A7: U15201000678 | B7: EQUIPO DE ENSAYO DE PLACA DE CARGA | C7: EQUIPO LABORATORIO - VIGAS BENKELMAN DOBLE PARA MEDIR EL RADIO CORVATURA DEL ASFAL | D7: Académica | E7: CIPAV | G7: =IFERROR(VLOOKUP(D7,Listas!$A$2:$B$20,2,FALSE()),999) -> 1 | H7: =IF(F7="","Sin fecha",IF(TODAY()-F7>180,"Revisar",IF(TODAY()-F7>90,"Próximo","Vigente"))) -> Sin fecha | J7: 120 | K7: 8 | L7: 46023 | M7: N
A8: U15201000677 | B8: Manual de Operación: Punto de Reblandecimiento del Asfalto | C8: EQUIPO LABORATORIO - PROBADOR AUTOMATICO DE ANILLO Y BOLA O PUNTO DE ABLANDAMIENTO. | D8: Académica | E8: CIPAV | G8: =IFERROR(VLOOKUP(D8,Listas!$A$2:$B$20,2,FALSE()),999) -> 1 | H8: =IF(F8="","Sin fecha",IF(TODAY()-F8>180,"Revisar",IF(TODAY()-F8>90,"Próximo","Vigente"))) -> Sin fecha | J8: 120 | K8: 8 | L8: 46023 | M8: N
A9: U15201000668 | B9: PERMEÁMETRO MULTIPROPÓSITO PARA ENSAYOS DE PERMEABILIDAD EN SUELOS | C9: EQUIPO LABORATORIO - CONSTRUCCIÓN, ENSAMBLAJE Y SUMINISTRO DE UN DISPOSITIVO PERMEÁMETRO MULTIPROPÓSITO, SEGÚN DISEÑO ESCOGIDO POR EL CLIENTE REF: PER001 | D9: Académica | E9: CIPAV | G9: =IFERROR(VLOOKUP(D9,Listas!$A$2:$B$20,2,FALSE()),999) -> 1 | H9: =IF(F9="","Sin fecha",IF(TODAY()-F9>180,"Revisar",IF(TODAY()-F9>90,"Próximo","Vigente"))) -> Sin fecha | J9: 120 | K9: 8 | L9: 46023 | M9: N
A10: U15201000010 | B10: VISCOSÍMETRO DIGITAL BROOKFIELD PARA ENSAYOS DE VISCOSIDAD EN CEMENTOS ASFÁLTICOS | C10: EQUIPO LABORATORIO PENETRO-METRO . PROVEEDOR:890704382 UNIVERSIDAD DE IBAGUE | D10: Académica | E10: CIPAV | G10: =IFERROR(VLOOKUP(D10,Listas!$A$2:$B$20,2,FALSE()),999) -> 1 | H10: =IF(F10="","Sin fecha",IF(TODAY()-F10>180,"Revisar",IF(TODAY()-F10>90,"Próximo","Vigente"))) -> Sin fecha | J10: 120 | K10: 120 | L10: 41090 | M10: S
A11: U15201000407 | B11: Ac voltage/current data loger | C11: EQUIPO LABORATORIO ANALIZADOR DE CORRIENTE EXTECH. PROVEEDOR:93411261 HERNAN DARIO QUIÑONES | D11: Académica | E11: Energías renovables | G11: =IFERROR(VLOOKUP(D11,Listas!$A$2:$B$20,2,FALSE()),999) -> 1 | H11: =IF(F11="","Sin fecha",IF(TODAY()-F11>180,"Revisar",IF(TODAY()-F11>90,"Próximo","Vigente"))) -> Sin fecha | J11: 1 | K11: 1 | L11: 42886 | M11: S
A12: U15201000408 | B12: Ac voltage/current data loger | C12: EQUIPO LABORATORIO ANALIZADOR DE CORRIENTE EXTECH. PROVEEDOR:890704382 UNIVERSIDAD DE IBAGUE | D12: Académica | E12: Energías renovables | G12: =IFERROR(VLOOKUP(D12,Listas!$A$2:$B$20,2,FALSE()),999) -> 1 | H12: =IF(F12="","Sin fecha",IF(TODAY()-F12>180,"Revisar",IF(TODAY()-F12>90,"Próximo","Vigente"))) -> Sin fecha | J12: 1 | K12: 1 | L12: 42886 | M12: S
A13: U15201000409 | B13: Ac voltage/current data loger | C13: EQUIPO LABORATORIO ANALIZADOR DE CORRIENTE EXTECH. PROVEEDOR:890704382 UNIVERSIDAD DE IBAGUE | D13: Académica | E13: Energías renovables | G13: =IFERROR(VLOOKUP(D13,Listas!$A$2:$B$20,2,FALSE()),999) -> 1 | H13: =IF(F13="","Sin fecha",IF(TODAY()-F13>180,"Revisar",IF(TODAY()-F13>90,"Próximo","Vigente"))) -> Sin fecha | J13: 1 | K13: 1 | L13: 42886 | M13: S
A14: U15201000413 | B14: Ac voltage/current data loger | C14: EQUIPO LABORATORIO ANALIZADOR DE CORRIENTE MARCA ERASMUS MODELO EDL - 10. PROVEEDOR:890704382 UNIVERSIDAD DE IBAGUE | D14: Académica | E14: Energías renovables | G14: =IFERROR(VLOOKUP(D14,Listas!$A$2:$B$20,2,FALSE()),999) -> 1 | H14: =IF(F14="","Sin fecha",IF(TODAY()-F14>180,"Revisar",IF(TODAY()-F14>90,"Próximo","Vigente"))) -> Sin fecha | J14: 1 | K14: 1 | L14: 42886 | M14: S
A15: U15201000414 | B15: Ac voltage/current data loger | C15: EQUIPO LABORATORIO ANALIZADOR DE CORRIENTE EXTECH. PROVEEDOR:890704382 UNIVERSIDAD DE IBAGUE | D15: Académica | E15: Energías renovables | G15: =IFERROR(VLOOKUP(D15,Listas!$A$2:$B$20,2,FALSE()),999) -> 1 | H15: =IF(F15="","Sin fecha",IF(TODAY()-F15>180,"Revisar",IF(TODAY()-F15>90,"Próximo","Vigente"))) -> Sin fecha | J15: 1 | K15: 1 | L15: 42886 | M15: S
A16: U15201000415 | B16: Ac voltage/current data loger | C16: EQUIPO LABORATORIO ANALIZADOR DE CORRIENTE EXTECH. PROVEEDOR:890704382 UNIVERSIDAD DE IBAGUE | D16: Académica | E16: Energías renovables | G16: =IFERROR(VLOOKUP(D16,Listas!$A$2:$B$20,2,FALSE()),999) -> 1 | H16: =IF(F16="","Sin fecha",IF(TODAY()-F16>180,"Revisar",IF(TODAY()-F16>90,"Próximo","Vigente"))) -> Sin fecha | J16: 1 | K16: 1 | L16: 42886 | M16: S
... A43: U15201001163 | B43: BALANZA ANALITICA | C43: BALANZA - BALANZA DIGITAL: BALANZA ANALITICA, TUNING FORK SENSOR, CALIBRACION EXTERNA CAP 220 G LEG 0.0001 G REF HT224 MARCA VIBRA | D43: Académica | E43: Lab. de Diseño de Sistemas Mecanicos | G43: =IFERROR(VLOOKUP(D43,Listas!$A$2:$B$20,2,FALSE()),999) -> 1 | H43: =IF(F43="","Sin fecha",IF(TODAY()-F43>180,"Revisar",IF(TODAY()-F43>90,"Próximo","Vigente"))) -> Sin fecha | J43: 120 | K43: 60 | L43: 44440 | M43: N
A44: U15200500130 | B44: BANCO DE ENSAYOS DE EXTREMA PRESION | C44: MAQUINARIA Y EQUIPO BANCO PARA ENSAYOS DE EXTREMA PRESION EN ACEITE LUBRICANTES . PROVEEDOR:890704382 UNIVERSIDAD DE IBAGUE | D44: Académica | E44: Lab. de Diseño de Sistemas Mecanicos | F44: 46244 | G44: =IFERROR(VLOOKUP(D44,Listas!$A$2:$B$20,2,FALSE()),999) -> 1 | H44: =IF(F44="","Sin fecha",IF(TODAY()-F44>180,"Revisar",IF(TODAY()-F44>90,"Próximo","Vigente"))) -> Vigente | J44: 120 | K44: 120 | L44: 41090 | M44: S
A45: U15200500133 | B45: BANCO DE VIBRACIONES | C45: MAQUINARIA Y EQUIPO BANCO PARA ENSAYO PARA VIBRACIONES . PROVEEDOR:890704382 UNIVERSIDAD DE IBAGUE | D45: Académica | E45: Lab. de Diseño de Sistemas Mecanicos | G45: =IFERROR(VLOOKUP(D45,Listas!$A$2:$B$20,2,FALSE()),999) -> 1 | H45: =IF(F45="","Sin fecha",IF(TODAY()-F45>180,"Revisar",IF(TODAY()-F45>90,"Próximo","Vigente"))) -> Sin fecha | J45: 120 | K45: 120 | L45: 41090 | M45: S
A46: U15200500131 | B46: BANCO PIN ON DISC | C46: MAQUINARIA Y EQUIPO PIN ON DISC. PROVEEDOR:890704382 UNIVERSIDAD DE IBAGUE | D46: Académica | E46: Lab. de Diseño de Sistemas Mecanicos | G46: =IFERROR(VLOOKUP(D46,Listas!$A$2:$B$20,2,FALSE()),999) -> 1 | H46: =IF(F46="","Sin fecha",IF(TODAY()-F46>180,"Revisar",IF(TODAY()-F46>90,"Próximo","Vigente"))) -> Sin fecha | J46: 120 | K46: 120 | L46: 41090 | M46: S
A47: U15201001146 | B47: CAMARA TERMOGRAFICA | C47: CAMARA TERMOGRAFICA - W8060 | D47: Académica | E47: Lab. de Diseño de Sistemas Mecanicos | G47: =IFERROR(VLOOKUP(D47,Listas!$A$2:$B$20,2,FALSE()),999) -> 1 | H47: =IF(F47="","Sin fecha",IF(TODAY()-F47>180,"Revisar",IF(TODAY()-F47>90,"Próximo","Vigente"))) -> Sin fecha | J47: 120 | K47: 85 | L47: 43706 | M47: N
A48: U15200503445 | B48: DESHUMIDIFICADOR | C48: DESHUMIDIFICADOR ELECTROLUX MODELO FFAD2234W1 115 VOLTS SERVICE MODEL FFAD2234W10 | D48: Académica | E48: Lab. de Diseño de Sistemas Mecanicos | G48: =IFERROR(VLOOKUP(D48,Listas!$A$2:$B$20,2,FALSE()),999) -> 1 | H48: =IF(F48="","Sin fecha",IF(TODAY()-F48>180,"Revisar",IF(TODAY()-F48>90,"Próximo","Vigente"))) -> Sin fecha | J48: 120 | K48: 20 | L48: 45658 | M48: N
A49: U15201001225 | B49: EQUIPO DE VIBRACIONES | C49: EQUIPO DE VIBRACIONES ERBESSD | D49: Académica | E49: Lab. de Diseño de Sistemas Mecanicos | G49: =IFERROR(VLOOKUP(D49,Listas!$A$2:$B$20,2,FALSE()),999) -> 1 | H49: =IF(F49="","Sin fecha",IF(TODAY()-F49>180,"Revisar",IF(TODAY()-F49>90,"Próximo","Vigente"))) -> Sin fecha | J49: 1 | K49: 1 | L49: 44986 | M49: S
A50: U15201000162 | B50: LAMPARA ESTROBOSCOPICA | C50: EQUIPO LABORATORIO LAMPARA ESTREBOSTROPICA MARCA SKF MODELO TKRS20. PROVEEDOR:890704382 UNIVERSIDAD DE IBAGUE | D50: Académica | E50: Lab. de Diseño de Sistemas Mecanicos | G50: =IFERROR(VLOOKUP(D50,Listas!$A$2:$B$20,2,FALSE()),999) -> 1 | H50: =IF(F50="","Sin fecha",IF(TODAY()-F50>180,"Revisar",IF(TODAY()-F50>90,"Próximo","Vigente"))) -> Sin fecha | J50: 120 | K50: 120 | L50: 41090 | M50: S
A51: U15200500132 | B51: MOTOR BANCO DE TRANSMISION | C51: MAQUINARIA Y EQUIPO MOTOR - BANCO PARA ENSAYOS DE TRANSMISION O ENLASES FLEXIBLES . PROVEEDOR:890704382 UNIVERSIDAD DE IBAGUE | D51: Académica | E51: Lab. de Diseño de Sistemas Mecanicos | G51: =IFERROR(VLOOKUP(D51,Listas!$A$2:$B$20,2,FALSE()),999) -> 1 | H51: =IF(F51="","Sin fecha",IF(TODAY()-F51>180,"Revisar",IF(TODAY()-F51>90,"Próximo","Vigente"))) -> Sin fecha | J51: 120 | K51: 120 | L51: 41090 | M51: S
A52: U15280502039 | B52: PC WORKSTATION | C52: ESTACION DE TRABAJO - TORRE DELL PRECISION 5820 XCTO BASE - 1028387277809 PROCESADOR INTEL® XEON® W-2145 3.7GHZ, 4.5GHZ TURBO, 8C, 11M CACHE, HT, (140W) DDR4-2666 WINDOWS® 10 PRO PARA WORKSTATION (4 NÚCLEOS PLUS) ESPAÑOL PRUEBA DE 30 DÍAS DE MICROSOFT OFFICE DUAL NVIDIA® QUADRO®P1000, 4GB, 4 MDP (5820T) MOD; DIMM; 64 G; 4 X 16 G; 2667; RDIM UNIDAD DE ESTADO SÓLIDO CLASE 20 SATA DE 512 GB Y 2,5" DISCO DURO SATA DE 3,5 GB - 2 TB DE 7200 RPM UNIDAD ÓPTICA 8X DELGADA (DVD +/- RW) TECLADO CON CABLE DELL KB216, ESPAÑOL MOUSE CABLEADO DELL MS116; NEGRO 3 AÑOS DE PROSUPPORT CON SERVICIO EN SITIO AL SIGUIENTE DÍA LABORABLE DELL 24 MONITOR | P2417H | D52: Académica | E52: Lab. de Diseño de Sistemas Mecanicos | G52: =IFERROR(VLOOKUP(D52,Listas!$A$2:$B$20,2,FALSE()),999) -> 1 | H52: =IF(F52="","Sin fecha",IF(TODAY()-F52>180,"Revisar",IF(TODAY()-F52>90,"Próximo","Vigente"))) -> Sin fecha | J52: 60 | K52: 60 | L52: 43425 | M52: S
A53: U15200500518 | B53: PINZA VOLTIAMPERIMETRICA | C53: MAQUINARIA Y EQUIPO PINZAS VOLTIAMPERIMETRICA. PROVEEDOR:890704382 UNIVERSIDAD DE IBAGUE | D53: Académica | E53: Lab. de Diseño de Sistemas Mecanicos | G53: =IFERROR(VLOOKUP(D53,Listas!$A$2:$B$20,2,FALSE()),999) -> 1 | H53: =IF(F53="","Sin fecha",IF(TODAY()-F53>180,"Revisar",IF(TODAY()-F53>90,"Próximo","Vigente"))) -> Sin fecha | J53: 120 | K53: 120 | L53: 41090 | M53: S
A54: U15200500519 | B54: PINZA VOLTIAMPERIMETRICA | C54: MAQUINARIA Y EQUIPO PINZAS VOLTIAMPERIMETRICA. PROVEEDOR:890704382 UNIVERSIDAD DE IBAGUE | D54: Académica | E54: Lab. de Diseño de Sistemas Mecanicos | G54: =IFERROR(VLOOKUP(D54,Listas!$A$2:$B$20,2,FALSE()),999) -> 1 | H54: =IF(F54="","Sin fecha",IF(TODAY()-F54>180,"Revisar",IF(TODAY()-F54>90,"Próximo","Vigente"))) -> Sin fecha | J54: 120 | K54: 120 | L54: 41090 | M54: S
A55: U15201000070 | B55: PROTOTIPO CNC | C55: EQUIPO LABORATORIO PROTOTIPO DE MAQUINA CNC. PROVEEDOR:890704382 UNIVERSIDAD DE IBAGUE | D55: Académica | E55: Lab. de Diseño de Sistemas Mecanicos | G55: =IFERROR(VLOOKUP(D55,Listas!$A$2:$B$20,2,FALSE()),999) -> 1 | H55: =IF(F55="","Sin fecha",IF(TODAY()-F55>180,"Revisar",IF(TODAY()-F55>90,"Próximo","Vigente"))) -> Sin fecha | J55: 120 | K55: 120 | L55: 41090 | M55: S
A56: U15201001074 | B56: RUGOSIMETRO | C56: RUGOSIMETRO - TIME 3221 CON CARACTERÍSTICAS DE MEDICIÓN MULTIPARAMETRICA: RA, RP, RV, RT, RZ, RQ, RSK, RKU, RC, RPC, RSM, RMR (C), TP, RMR, RPM, RZ1MAX, RZJIS, RMAX, HTP, R¿C ,, R¿Q , R¿A, PA, PP, PV, PT, PZ, PQ, PSK, PKU, PC, PSM, PMR (C), PMR, PZ1MAX, PZJIS, P¿C, P¿Q RK, RPK, RVK, MR1, MR2, A1, A2 ; PASTILLA DE INDUCTANCIA DE ALTA PRECISIÓN MÉTODOS DE FILTRADO DE 2RC, GAUSS COMPATIBLE CON CUATRO ESTÁNDARES DE ISO1997, ANSI Y JIS2001. INCLUYE SOFTWARE NUESTRO TIME3221 SE PUEDE CONECTAR CON EL SOFTWARE, EN EL QUE PUEDE TRANSFERIR TODOS LOS DATOS A LA PC, INCLUIDAS LAS ONDAS | D56: Académica | E56: Lab. de Diseño de Sistemas Mecanicos | G56: =IFERROR(VLOOKUP(D56,Listas!$A$2:$B$20,2,FALSE()),999) -> 1 | H56: =IF(F56="","Sin fecha",IF(TODAY()-F56>180,"Revisar",IF(TODAY()-F56>90,"Próximo","Vigente"))) -> Sin fecha | J56: 120 | K56: 93 | L56: 43457 | M56: N
... A79: U15200503414 | B79: VIDEOBEAM | C79: VIDEOPROYECTOR LS610WH-4,0 LS610WH-4,000 ANSI LUMENS IEWSONIC WXGA LED PROJECTOR 4,000 ANSI UMENS WXGA LED USINESS/EDUCATION PROJECTOR TECNOLOGÍA LED DE 3ª GENERACIÓN PARA UNA MAYOR SOSTENIBILIDAD SIN MANTENIMIENTO: 60.000 HORAS DE VIDA ÚTIL DE LA FUENTE LUMINOSA Y MENOR CONSUMO DE ENERGÍA 4.000 ANSI LÚMENES PARA IMÁGENES BRILLANTES EN CUALQUIER ENTORNO FACILIDAD DE USO: ON/OFF INSTANTÁNEO KEYSTONE H/V Y CONTROL LAN AMPLIA GAMA CROMÁTICA PARA PRESENTACIONES DE ALTA CALIDAD | D79: Académica | E79: Lab. de Diseño Mecatronico | G79: =IFERROR(VLOOKUP(D79,Listas!$A$2:$B$20,2,FALSE()),999) -> 1 | H79: =IF(F79="","Sin fecha",IF(TODAY()-F79>180,"Revisar",IF(TODAY()-F79>90,"Próximo","Vigente"))) -> Sin fecha | J79: 120 | K79: 27 | L79: 45444 | M79: N
A80: U15200500954 | B80: FUENTE DE PODER | C80: MAQUINARIA Y EQUIPO FUENTE DE PODER MARCA BECAP MODELO 1652. PROVEEDOR:890704382 UNIVERSIDAD DE IBAGUE | D80: Académica | E80: Lab. Electromedicina L4 | F80: 45992 | G80: =IFERROR(VLOOKUP(D80,Listas!$A$2:$B$20,2,FALSE()),999) -> 1 | H80: =IF(F80="","Sin fecha",IF(TODAY()-F80>180,"Revisar",IF(TODAY()-F80>90,"Próximo","Vigente"))) -> Revisar | J80: 120 | K80: 120 | L80: 41090 | M80: S
A81: U15200500955 | B81: FUENTE DE PODER | C81: MAQUINARIA Y EQUIPO FUENTE DE PODER MARCA BECAP MODELO 1652. PROVEEDOR:890704382 UNIVERSIDAD DE IBAGUE | D81: Académica | E81: Lab. Electromedicina L4 | F81: 45992 | G81: =IFERROR(VLOOKUP(D81,Listas!$A$2:$B$20,2,FALSE()),999) -> 1 | H81: =IF(F81="","Sin fecha",IF(TODAY()-F81>180,"Revisar",IF(TODAY()-F81>90,"Próximo","Vigente"))) -> Revisar | J81: 120 | K81: 120 | L81: 41090 | M81: S
A82: U15200500956 | B82: FUENTE DE PODER | C82: MAQUINARIA Y EQUIPO FUENTE DE PODER MARCA BECAP MODELO 1652. PROVEEDOR:890704382 UNIVERSIDAD DE IBAGUE | D82: Académica | E82: Lab. Electromedicina L4 | F82: 45992 | G82: =IFERROR(VLOOKUP(D82,Listas!$A$2:$B$20,2,FALSE()),999) -> 1 | H82: =IF(F82="","Sin fecha",IF(TODAY()-F82>180,"Revisar",IF(TODAY()-F82>90,"Próximo","Vigente"))) -> Revisar | J82: 120 | K82: 120 | L82: 41090 | M82: S
A83: U15200500957 | B83: FUENTE DE PODER | C83: MAQUINARIA Y EQUIPO FUENTE DE PODER MARCA BECAP MODELO 1652. PROVEEDOR:890704382 UNIVERSIDAD DE IBAGUE | D83: Académica | E83: Lab. Electromedicina L4 | F83: 45992 | G83: =IFERROR(VLOOKUP(D83,Listas!$A$2:$B$20,2,FALSE()),999) -> 1 | H83: =IF(F83="","Sin fecha",IF(TODAY()-F83>180,"Revisar",IF(TODAY()-F83>90,"Próximo","Vigente"))) -> Revisar | J83: 120 | K83: 120 | L83: 41090 | M83: S
A84: U15200500958 | B84: FUENTE DE PODER | C84: MAQUINARIA Y EQUIPO FUENTE DE PODER MARCA BECAP MODELO 1652. PROVEEDOR:890704382 UNIVERSIDAD DE IBAGUE | D84: Académica | E84: Lab. Electromedicina L4 | F84: 45992 | G84: =IFERROR(VLOOKUP(D84,Listas!$A$2:$B$20,2,FALSE()),999) -> 1 | H84: =IF(F84="","Sin fecha",IF(TODAY()-F84>180,"Revisar",IF(TODAY()-F84>90,"Próximo","Vigente"))) -> Revisar | J84: 120 | K84: 120 | L84: 41090 | M84: S
A85: U15200501124 | B85: GENERADOR DE RF | C85: MAQUINARIA Y EQUIPO GENERADOR DE SEÑAL MARCA HP MODELO 8647A . PROVEEDOR:890704382 UNIVERSIDAD DE IBAGUE | D85: Académica | E85: Lab. Electromedicina L4 | F85: 45809 | G85: =IFERROR(VLOOKUP(D85,Listas!$A$2:$B$20,2,FALSE()),999) -> 1 | H85: =IF(F85="","Sin fecha",IF(TODAY()-F85>180,"Revisar",IF(TODAY()-F85>90,"Próximo","Vigente"))) -> Revisar | J85: 120 | K85: 120 | L85: 41090 | M85: S
A86: U15200501285 | B86: POWERLAB | C86: MAQUINARIA Y EQUIPO POWER LAB MARCA ADINTRUMENTS MODELO 15T. PROVEEDOR:890704382 UNIVERSIDAD DE IBAGUE | D86: Académica | E86: Lab. Electromedicina L4 | F86: 45809 | G86: =IFERROR(VLOOKUP(D86,Listas!$A$2:$B$20,2,FALSE()),999) -> 1 | H86: =IF(F86="","Sin fecha",IF(TODAY()-F86>180,"Revisar",IF(TODAY()-F86>90,"Próximo","Vigente"))) -> Revisar | J86: 120 | K86: 120 | L86: 41090 | M86: S
A87: U15200501286 | B87: POWERLAB | C87: MAQUINARIA Y EQUIPO POWER LAB MARCA ADINTRUMENTS MODELO 4856. PROVEEDOR:890704382 UNIVERSIDAD DE IBAGUE | D87: Académica | E87: Lab. Electromedicina L4 | F87: 45809 | G87: =IFERROR(VLOOKUP(D87,Listas!$A$2:$B$20,2,FALSE()),999) -> 1 | H87: =IF(F87="","Sin fecha",IF(TODAY()-F87>180,"Revisar",IF(TODAY()-F87>90,"Próximo","Vigente"))) -> Revisar | J87: 120 | K87: 120 | L87: 41090 | M87: S
A88: U15201000820 | B88: POWERLAB | C88: EQUIPO LABORATORIO - POWERLAB 15T REF ML4818; INCLUYE; TRANSDUCTOR DE PULSO REF TN1012/ST; CABLE BIO AMP BLINDADO DE 5 DONDUCTORES REF MLA2540; CABLES CONDUCTORES BLINDADOS (5 BROCES) REF MLA2505; ELECTRODO DE BARRA ESTIMULANTE REF MLADDF30; ELECTRODOS PLANOS PARA EEG REF MLAWBT9; MALETIN SISTEMA DE ENSEÑANZA REF SP0133; MICRÓFONO CARDIACO REF MLT201; MALETIN SISTEMA DE ENSEÑANZA THE SP0133 IS AN EMPLI STAINLESS STELL CASE WITH FOAM INSERTS FOR USE IN PACKAGING MANY OF THE ADINSTRUMENTS, TEACHING SYSTEM REF SP0133 | D88: Académica | E88: Lab. Electromedicina L4 | F88: 45809 | G88: =IFERROR(VLOOKUP(D88,Listas!$A$2:$B$20,2,FALSE()),999) -> 1 | H88: =IF(F88="","Sin fecha",IF(TODAY()-F88>180,"Revisar",IF(TODAY()-F88>90,"Próximo","Vigente"))) -> Revisar | J88: 120 | K88: 105 | L88: 43075 | M88: N
A89: U15201000768 | B89: ANALIZADOR DE ESPECTRO | C89: ANALIZADOR DE ESPECTO - RANGO DE FRECUENCIA 9 KHZ, CON SISTEMA DE DEMODULACION Y ANALISIS AM/FM/ASK/FSK, CONTADOR DE FRECUENCIA INCORPORADO, INCLUYE CABLE DE PODER, GUIA DE INICIO RÁPIDO, CERTIFICADO DE CALIBRACION, CD-ROM (MANUAL DE USUARIO, MANUAL DE PROGRAMACIÓN, SOFTWARE SPECTRUMSHOT, GUIA DE INICIO RAPIDO SPECTRUMSHOT Y CONTOLADORES IVI, MARCA INSTEK, MODELO GSP-9300, PAQUETE DE BATERIAS DC, DURACION REMOTA POR 2 HORAS | D89: Académica | E89: Lab. Electrónica General (L1) | F89: 45809 | G89: =IFERROR(VLOOKUP(D89,Listas!$A$2:$B$20,2,FALSE()),999) -> 1 | H89: =IF(F89="","Sin fecha",IF(TODAY()-F89>180,"Revisar",IF(TODAY()-F89>90,"Próximo","Vigente"))) -> Revisar | J89: 120 | K89: 106 | L89: 43050 | M89: N
A90: U15201000827 | B90: ANALIZADOR DE ESPECTRO | C90: ANALIZADOR DE ESPECTO - RANGO DE FRECUENCIA 9 KHZ, CON SISTEMA DE DEMODULACION Y ANALISIS AM/FM/ASK/FSK, CONTADOR DE FRECUENCIA INCORPORADO, INCLUYE CABLE DE PODER, GUIA DE INICIO RÁPIDO, CERTIFICADO DE CALIBRACION, CD-ROM (MANUAL DE USUARIO, MANUAL DE PROGRAMACIÓN, SOFTWARE SPECTRUMSHOT, GUIA DE INICIO RAPIDO SPECTRUMSHOT Y CONTOLADORES IVI, MARCA INSTEK, MODELO GSP-9300, PAQUETE DE BATERIAS DC, DURACION REMOTA POR 2 HORAS | D90: Académica | E90: Lab. Electrónica General (L1) | F90: 45809 | G90: =IFERROR(VLOOKUP(D90,Listas!$A$2:$B$20,2,FALSE()),999) -> 1 | H90: =IF(F90="","Sin fecha",IF(TODAY()-F90>180,"Revisar",IF(TODAY()-F90>90,"Próximo","Vigente"))) -> Revisar | J90: 120 | K90: 106 | L90: 43050 | M90: N
A91: U15280500915 | B91: EQUIPO DE COMPUTO | C91: EQUIPOS DE COMPUTO COMPUTADOR DE MESA MARCA DELL. PROVEEDOR:890704382 UNIVERSIDAD DE IBAGUE | D91: Académica | E91: Lab. Electrónica General (L1) | F91: 46023 | G91: =IFERROR(VLOOKUP(D91,Listas!$A$2:$B$20,2,FALSE()),999) -> 1 | H91: =IF(F91="","Sin fecha",IF(TODAY()-F91>180,"Revisar",IF(TODAY()-F91>90,"Próximo","Vigente"))) -> Revisar | J91: 60 | K91: 60 | L91: 41455 | M91: S
A92: U15280506139 | B92: EQUIPO DE COMPUTO | C92: EQUIPOS DE COMPUTO LEASING -ACTIVO CREADO AUTOMATICAMENTE POR PROCESO DE OPCION DE COMPRA DEL ACTIVO # 34965 | D92: Académica | E92: Lab. Electrónica General (L1) | G92: =IFERROR(VLOOKUP(D92,Listas!$A$2:$B$20,2,FALSE()),999) -> 1 | H92: =IF(F92="","Sin fecha",IF(TODAY()-F92>180,"Revisar",IF(TODAY()-F92>90,"Próximo","Vigente"))) -> Sin fecha | J92: 60 | K92: 60 | L92: 43464 | M92: S
A93: U15201001147 | B93: ESTACION DE SOLDADURA | C93: ESTACION DE SOLDADURA - ESTACIÓN DE SOLDADURA BAKU BK702B | D93: Académica | E93: Lab. Electrónica General (L1) | F93: 45992 | G93: =IFERROR(VLOOKUP(D93,Listas!$A$2:$B$20,2,FALSE()),999) -> 1 | H93: =IF(F93="","Sin fecha",IF(TODAY()-F93>180,"Revisar",IF(TODAY()-F93>90,"Próximo","Vigente"))) -> Revisar | J93: 120 | K93: 85 | L93: 43695 | M93: N
A94: U15200501103 | B94: FRECUENCIMETRO | C94: MAQUINARIA Y EQUIPO CONTADOR DE FRECUENCIA MARCA HP MODELO 5381A. PROVEEDOR:890704382 UNIVERSIDAD DE IBAGUE | D94: Académica | E94: Lab. Electrónica General (L1) | F94: 46023 | G94: =IFERROR(VLOOKUP(D94,Listas!$A$2:$B$20,2,FALSE()),999) -> 1 | H94: =IF(F94="","Sin fecha",IF(TODAY()-F94>180,"Revisar",IF(TODAY()-F94>90,"Próximo","Vigente"))) -> Revisar | J94: 120 | K94: 120 | L94: 39263 | M94: S
A95: U15200501104 | B95: FRECUENCIMETRO | C95: MAQUINARIA Y EQUIPO CONTADOR DE FRECUENCIA MARCA HP MODELO 5381A. PROVEEDOR:890704382 UNIVERSIDAD DE IBAGUE | D95: Académica | E95: Lab. Electrónica General (L1) | F95: 46023 | G95: =IFERROR(VLOOKUP(D95,Listas!$A$2:$B$20,2,FALSE()),999) -> 1 | H95: =IF(F95="","Sin fecha",IF(TODAY()-F95>180,"Revisar",IF(TODAY()-F95>90,"Próximo","Vigente"))) -> Revisar | J95: 120 | K95: 120 | L95: 39263 | M95: S
A96: U15200501105 | B96: FRECUENCIMETRO | C96: MAQUINARIA Y EQUIPO CONTADOR DE FRECUENCIA MARCA HP MODELO 5381A. PROVEEDOR:890704382 UNIVERSIDAD DE IBAGUE | D96: Académica | E96: Lab. Electrónica General (L1) | F96: 46023 | G96: =IFERROR(VLOOKUP(D96,Listas!$A$2:$B$20,2,FALSE()),999) -> 1 | H96: =IF(F96="","Sin fecha",IF(TODAY()-F96>180,"Revisar",IF(TODAY()-F96>90,"Próximo","Vigente"))) -> Revisar | J96: 120 | K96: 120 | L96: 39263 | M96: S
A97: U15200500959 | B97: FUENTE DE PODER | C97: MAQUINARIA Y EQUIPO FUENTE DE PODER MARCA ARKSEN MODELO 303-2D. PROVEEDOR:890704382 UNIVERSIDAD DE IBAGUE | D97: Académica | E97: Lab. Electrónica General (L1) | F97: 45809 | G97: =IFERROR(VLOOKUP(D97,Listas!$A$2:$B$20,2,FALSE()),999) -> 1 | H97: =IF(F97="","Sin fecha",IF(TODAY()-F97>180,"Revisar",IF(TODAY()-F97>90,"Próximo","Vigente"))) -> Revisar | J97: 120 | K97: 120 | L97: 41090 | M97: S
A98: U15200500983 | B98: FUENTE DE PODER | C98: MAQUINARIA Y EQUIPO FUENTE DE PODER MARCA ERASMUS . PROVEEDOR:890704382 UNIVERSIDAD DE IBAGUE | D98: Académica | E98: Lab. Electrónica General (L1) | F98: 45809 | G98: =IFERROR(VLOOKUP(D98,Listas!$A$2:$B$20,2,FALSE()),999) -> 1 | H98: =IF(F98="","Sin fecha",IF(TODAY()-F98>180,"Revisar",IF(TODAY()-F98>90,"Próximo","Vigente"))) -> Revisar | J98: 120 | K98: 120 | L98: 41090 | M98: S
A99: U15200500984 | B99: FUENTE DE PODER | C99: MAQUINARIA Y EQUIPO FUENTE DE PODER MARCA ERASMUS . PROVEEDOR:890704382 UNIVERSIDAD DE IBAGUE | D99: Académica | E99: Lab. Electrónica General (L1) | F99: 45809 | G99: =IFERROR(VLOOKUP(D99,Listas!$A$2:$B$20,2,FALSE()),999) -> 1 | H99: =IF(F99="","Sin fecha",IF(TODAY()-F99>180,"Revisar",IF(TODAY()-F99>90,"Próximo","Vigente"))) -> Revisar | J99: 120 | K99: 120 | L99: 41090 | M99: S
A100: U15200500999 | B100: FUENTE DE PODER | C100: MAQUINARIA Y EQUIPO FUENTE DE PODER MARCA ERASMUS REF. EF0055. PROVEEDOR:890704382 UNIVERSIDAD DE IBAGUE | D100: Académica | E100: Lab. Electrónica General (L1) | F100: 45809 | G100: =IFERROR(VLOOKUP(D100,Listas!$A$2:$B$20,2,FALSE()),999) -> 1 | H100: =IF(F100="","Sin fecha",IF(TODAY()-F100>180,"Revisar",IF(TODAY()-F100>90,"Próximo","Vigente"))) -> Revisar | J100: 120 | K100: 120 | L100: 40663 | M100: S
A101: U15200501027 | B101: FUENTE DE PODER | C101: MAQUINARIA Y EQUIPO FUENTE DE PODER MARCA GWINSETK REF. GPE3323. PROVEEDOR:890704382 UNIVERSIDAD DE IBAGUE | D101: Académica | E101: Lab. Electrónica General (L1) | F101: 45809 | G101: =IFERROR(VLOOKUP(D101,Listas!$A$2:$B$20,2,FALSE()),999) -> 1 | H101: =IF(F101="","Sin fecha",IF(TODAY()-F101>180,"Revisar",IF(TODAY()-F101>90,"Próximo","Vigente"))) -> Revisar | J101: 120 | K101: 117 | L101: 42735 | M101: N
A102: U15200501028 | B102: FUENTE DE PODER | C102: MAQUINARIA Y EQUIPO FUENTE DE PODER MARCA GWINSETK REF. GPE3323. PROVEEDOR:890704382 UNIVERSIDAD DE IBAGUE | D102: Académica | E102: Lab. Electrónica General (L1) | F102: 45809 | G102: =IFERROR(VLOOKUP(D102,Listas!$A$2:$B$20,2,FALSE()),999) -> 1 | H102: =IF(F102="","Sin fecha",IF(TODAY()-F102>180,"Revisar",IF(TODAY()-F102>90,"Próximo","Vigente"))) -> Revisar | J102: 120 | K102: 117 | L102: 42735 | M102: N
A103: U15200501029 | B103: FUENTE DE PODER | C103: MAQUINARIA Y EQUIPO FUENTE DE PODER MARCA GWINSETK REF. GPE3323. PROVEEDOR:890704382 UNIVERSIDAD DE IBAGUE | D103: Académica | E103: Lab. Electrónica General (L1) | F103: 45809 | G103: =IFERROR(VLOOKUP(D103,Listas!$A$2:$B$20,2,FALSE()),999) -> 1 | H103: =IF(F103="","Sin fecha",IF(TODAY()-F103>180,"Revisar",IF(TODAY()-F103>90,"Próximo","Vigente"))) -> Revisar | J103: 120 | K103: 117 | L103: 42735 | M103: N
A104: U15200501033 | B104: FUENTE DE PODER | C104: MAQUINARIA Y EQUIPO FUENTE DE PODER MARCA GWINSETK REF. GYC30300. PROVEEDOR:830037278 NUEVA ERA SOLUCIONES SAS | D104: Académica | E104: Lab. Electrónica General (L1) | F104: 45809 | G104: =IFERROR(VLOOKUP(D104,Listas!$A$2:$B$20,2,FALSE()),999) -> 1 | H104: =IF(F104="","Sin fecha",IF(TODAY()-F104>180,"Revisar",IF(TODAY()-F104>90,"Próximo","Vigente"))) -> Revisar | J104: 1 | K104: 1 | L104: 42886 | M104: S
... A166: U15200501084 | B166: MEDIDOR DE RPM | C166: MAQUINARIA Y EQUIPO MEDIDOR DE RPM. PROVEEDOR:890704382 UNIVERSIDAD DE IBAGUE | D166: Académica | E166: Lab. Electrónica General (L1) | F166: 45992 | G166: =IFERROR(VLOOKUP(D166,Listas!$A$2:$B$20,2,FALSE()),999) -> 1 | H166: =IF(F166="","Sin fecha",IF(TODAY()-F166>180,"Revisar",IF(TODAY()-F166>90,"Próximo","Vigente"))) -> Revisar | J166: 120 | K166: 120 | L166: 39263 | M166: S
A167: U15200501085 | B167: MEDIDOR DE RPM | C167: MAQUINARIA Y EQUIPO MEDIDOR DE RPM. PROVEEDOR:890704382 UNIVERSIDAD DE IBAGUE | D167: Académica | E167: Lab. Electrónica General (L1) | G167: =IFERROR(VLOOKUP(D167,Listas!$A$2:$B$20,2,FALSE()),999) -> 1 | H167: =IF(F167="","Sin fecha",IF(TODAY()-F167>180,"Revisar",IF(TODAY()-F167>90,"Próximo","Vigente"))) -> Sin fecha | J167: 120 | K167: 120 | L167: 39263 | M167: S
A168: U15200501086 | B168: MEDIDOR DE RPM | C168: MAQUINARIA Y EQUIPO MEDIDOR DE RPM. PROVEEDOR:890704382 UNIVERSIDAD DE IBAGUE | D168: Académica | E168: Lab. Electrónica General (L1) | F168: 45992 | G168: =IFERROR(VLOOKUP(D168,Listas!$A$2:$B$20,2,FALSE()),999) -> 1 | H168: =IF(F168="","Sin fecha",IF(TODAY()-F168>180,"Revisar",IF(TODAY()-F168>90,"Próximo","Vigente"))) -> Revisar | J168: 120 | K168: 120 | L168: 41090 | M168: S
A169: U15200501087 | B169: MEDIDOR DE RPM | C169: MAQUINARIA Y EQUIPO MEDIDOR DE RPM. PROVEEDOR:890704382 UNIVERSIDAD DE IBAGUE | D169: Académica | E169: Lab. Electrónica General (L1) | G169: =IFERROR(VLOOKUP(D169,Listas!$A$2:$B$20,2,FALSE()),999) -> 1 | H169: =IF(F169="","Sin fecha",IF(TODAY()-F169>180,"Revisar",IF(TODAY()-F169>90,"Próximo","Vigente"))) -> Sin fecha | J169: 120 | K169: 120 | L169: 41090 | M169: S
A170: U15200500933 | B170: MULTIMETRO | C170: MAQUINARIA Y EQUIPO MULTIMETRO . PROVEEDOR:890704382 UNIVERSIDAD DE IBAGUE | D170: Académica | E170: Lab. Electrónica General (L1) | F170: 46023 | G170: =IFERROR(VLOOKUP(D170,Listas!$A$2:$B$20,2,FALSE()),999) -> 1 | H170: =IF(F170="","Sin fecha",IF(TODAY()-F170>180,"Revisar",IF(TODAY()-F170>90,"Próximo","Vigente"))) -> Revisar | J170: 1 | K170: 1 | L170: 42886 | M170: S
A171: U15200500934 | B171: MULTIMETRO | C171: MAQUINARIA Y EQUIPO MULTIMETRO . PROVEEDOR:890704382 UNIVERSIDAD DE IBAGUE | D171: Académica | E171: Lab. Electrónica General (L1) | F171: 46023 | G171: =IFERROR(VLOOKUP(D171,Listas!$A$2:$B$20,2,FALSE()),999) -> 1 | H171: =IF(F171="","Sin fecha",IF(TODAY()-F171>180,"Revisar",IF(TODAY()-F171>90,"Próximo","Vigente"))) -> Revisar | J171: 120 | K171: 116 | L171: 42766 | M171: N
A172: U15200500935 | B172: MULTIMETRO | C172: MAQUINARIA Y EQUIPO MULTIMETRO . PROVEEDOR:890704382 UNIVERSIDAD DE IBAGUE | D172: Académica | E172: Lab. Electrónica General (L1) | F172: 46023 | G172: =IFERROR(VLOOKUP(D172,Listas!$A$2:$B$20,2,FALSE()),999) -> 1 | H172: =IF(F172="","Sin fecha",IF(TODAY()-F172>180,"Revisar",IF(TODAY()-F172>90,"Próximo","Vigente"))) -> Revisar | J172: 120 | K172: 120 | L172: 40237 | M172: S
A173: U15200500936 | B173: MULTIMETRO | C173: MAQUINARIA Y EQUIPO MULTIMETRO . PROVEEDOR:890704382 UNIVERSIDAD DE IBAGUE | D173: Académica | E173: Lab. Electrónica General (L1) | F173: 46023 | G173: =IFERROR(VLOOKUP(D173,Listas!$A$2:$B$20,2,FALSE()),999) -> 1 | H173: =IF(F173="","Sin fecha",IF(TODAY()-F173>180,"Revisar",IF(TODAY()-F173>90,"Próximo","Vigente"))) -> Revisar | J173: 120 | K173: 120 | L173: 40237 | M173: S
A174: U15200500937 | B174: MULTIMETRO | C174: MAQUINARIA Y EQUIPO MULTIMETRO . PROVEEDOR:890704382 UNIVERSIDAD DE IBAGUE | D174: Académica | E174: Lab. Electrónica General (L1) | F174: 46023 | G174: =IFERROR(VLOOKUP(D174,Listas!$A$2:$B$20,2,FALSE()),999) -> 1 | H174: =IF(F174="","Sin fecha",IF(TODAY()-F174>180,"Revisar",IF(TODAY()-F174>90,"Próximo","Vigente"))) -> Revisar | J174: 120 | K174: 120 | L174: 41090 | M174: S
A175: U15200501016 | B175: MULTIMETRO | C175: MAQUINARIA Y EQUIPO MULTIMETRO DIGITAL REF 34401A . PROVEEDOR:890704382 UNIVERSIDAD DE IBAGUE | D175: Académica | E175: Lab. Electrónica General (L1) | F175: 46023 | G175: =IFERROR(VLOOKUP(D175,Listas!$A$2:$B$20,2,FALSE()),999) -> 1 | H175: =IF(F175="","Sin fecha",IF(TODAY()-F175>180,"Revisar",IF(TODAY()-F175>90,"Próximo","Vigente"))) -> Revisar | J175: 120 | K175: 120 | L175: 39263 | M175: S
A176: U15200501108 | B176: MULTIMETRO | C176: MAQUINARIA Y EQUIPO MULTIMETRO DIGITAL REF 34401A MARCA AGINET . PROVEEDOR:890704382 UNIVERSIDAD DE IBAGUE | D176: Académica | E176: Lab. Electrónica General (L1) | F176: 46023 | G176: =IFERROR(VLOOKUP(D176,Listas!$A$2:$B$20,2,FALSE()),999) -> 1 | H176: =IF(F176="","Sin fecha",IF(TODAY()-F176>180,"Revisar",IF(TODAY()-F176>90,"Próximo","Vigente"))) -> Revisar | J176: 120 | K176: 120 | L176: 39263 | M176: S
A177: U15200501109 | B177: MULTIMETRO | C177: MAQUINARIA Y EQUIPO MULTIMETRO DIGITAL REF 34401A MARCA AGINET . PROVEEDOR:890704382 UNIVERSIDAD DE IBAGUE | D177: Académica | E177: Lab. Electrónica General (L1) | F177: 46023 | G177: =IFERROR(VLOOKUP(D177,Listas!$A$2:$B$20,2,FALSE()),999) -> 1 | H177: =IF(F177="","Sin fecha",IF(TODAY()-F177>180,"Revisar",IF(TODAY()-F177>90,"Próximo","Vigente"))) -> Revisar | J177: 120 | K177: 120 | L177: 39263 | M177: S
A178: U15200501110 | B178: MULTIMETRO | C178: MAQUINARIA Y EQUIPO MULTIMETRO DIGITAL REF 34401A MARCA AGINET . PROVEEDOR:890704382 UNIVERSIDAD DE IBAGUE | D178: Académica | E178: Lab. Electrónica General (L1) | F178: 46023 | G178: =IFERROR(VLOOKUP(D178,Listas!$A$2:$B$20,2,FALSE()),999) -> 1 | H178: =IF(F178="","Sin fecha",IF(TODAY()-F178>180,"Revisar",IF(TODAY()-F178>90,"Próximo","Vigente"))) -> Revisar | J178: 120 | K178: 120 | L178: 39263 | M178: S
A179: U15200501111 | B179: MULTIMETRO | C179: MAQUINARIA Y EQUIPO MULTIMETRO DIGITAL REF 34401A MARCA HP . PROVEEDOR:890704382 UNIVERSIDAD DE IBAGUE | D179: Académica | E179: Lab. Electrónica General (L1) | F179: 46023 | G179: =IFERROR(VLOOKUP(D179,Listas!$A$2:$B$20,2,FALSE()),999) -> 1 | H179: =IF(F179="","Sin fecha",IF(TODAY()-F179>180,"Revisar",IF(TODAY()-F179>90,"Próximo","Vigente"))) -> Revisar | J179: 120 | K179: 120 | L179: 39263 | M179: S
A180: U15200501112 | B180: MULTIMETRO | C180: MAQUINARIA Y EQUIPO MULTIMETRO DIGITAL REF 34401A MARCA HP . PROVEEDOR:890704382 UNIVERSIDAD DE IBAGUE | D180: Académica | E180: Lab. Electrónica General (L1) | F180: 46023 | G180: =IFERROR(VLOOKUP(D180,Listas!$A$2:$B$20,2,FALSE()),999) -> 1 | H180: =IF(F180="","Sin fecha",IF(TODAY()-F180>180,"Revisar",IF(TODAY()-F180>90,"Próximo","Vigente"))) -> Revisar | J180: 120 | K180: 120 | L180: 39263 | M180: S
A181: U15201001009 | B181: MULTIMETRO | C181: MULTIMETRO - MODELO: GDM-398 MULTIMETRO DIGITAL, VOLTAJE DC 1000V, VOLTAJE AC 750, CORRIENTE DC/AC 10A, CON MEDICIÓN DE DIODO, CONTINUIDAD, CICLO UTIL, BETA TRANSISTOR, RETENCIÓN DE DATOS, AUTORANGO, GARANTÍA 1 AÑO MARCA: INSTEK | D181: Académica | E181: Lab. Electrónica General (L1) | F181: 46023 | G181: =IFERROR(VLOOKUP(D181,Listas!$A$2:$B$20,2,FALSE()),999) -> 1 | H181: =IF(F181="","Sin fecha",IF(TODAY()-F181>180,"Revisar",IF(TODAY()-F181>90,"Próximo","Vigente"))) -> Revisar | J181: 120 | K181: 99 | L181: 43270 | M181: N
... A257: U15200501091 | B257: TERMOMETRO | C257: MAQUINARIA Y EQUIPO TERMOMETRO DIGITAL. PROVEEDOR:890704382 UNIVERSIDAD DE IBAGUE | D257: Académica | E257: Lab. Electrónica General (L1) | F257: 46023 | G257: =IFERROR(VLOOKUP(D257,Listas!$A$2:$B$20,2,FALSE()),999) -> 1 | H257: =IF(F257="","Sin fecha",IF(TODAY()-F257>180,"Revisar",IF(TODAY()-F257>90,"Próximo","Vigente"))) -> Revisar | J257: 120 | K257: 120 | L257: 41090 | M257: S
A258: U15200501092 | B258: TERMOMETRO | C258: MAQUINARIA Y EQUIPO TERMOMETRO DIGITAL. PROVEEDOR:890704382 UNIVERSIDAD DE IBAGUE | D258: Académica | E258: Lab. Electrónica General (L1) | G258: =IFERROR(VLOOKUP(D258,Listas!$A$2:$B$20,2,FALSE()),999) -> 1 | H258: =IF(F258="","Sin fecha",IF(TODAY()-F258>180,"Revisar",IF(TODAY()-F258>90,"Próximo","Vigente"))) -> Sin fecha | J258: 120 | K258: 120 | L258: 41090 | M258: S
A259: U15200501093 | B259: TERMOMETRO | C259: MAQUINARIA Y EQUIPO TERMOMETRO DIGITAL. PROVEEDOR:890704382 UNIVERSIDAD DE IBAGUE | D259: Académica | E259: Lab. Electrónica General (L1) | G259: =IFERROR(VLOOKUP(D259,Listas!$A$2:$B$20,2,FALSE()),999) -> 1 | H259: =IF(F259="","Sin fecha",IF(TODAY()-F259>180,"Revisar",IF(TODAY()-F259>90,"Próximo","Vigente"))) -> Sin fecha | J259: 120 | K259: 120 | L259: 41090 | M259: S
A260: U15200501066 | B260: TRANSMISOR DE PH | C260: MAQUINARIA Y EQUIPO MINI TRASMISOR DE PH MARCA NEWPORT MODELO PHTM-1. PROVEEDOR:890704382 UNIVERSIDAD DE IBAGUE | D260: Académica | E260: Lab. Electrónica General (L1) | F260: 46023 | G260: =IFERROR(VLOOKUP(D260,Listas!$A$2:$B$20,2,FALSE()),999) -> 1 | H260: =IF(F260="","Sin fecha",IF(TODAY()-F260>180,"Revisar",IF(TODAY()-F260>90,"Próximo","Vigente"))) -> Revisar | J260: 120 | K260: 120 | L260: 41090 | M260: S
A261: U15200501067 | B261: TRANSMISOR DE PH | C261: MAQUINARIA Y EQUIPO MINI TRASMISOR DE PH MARCA NEWPORT MODELO PHTM-1. PROVEEDOR:890704382 UNIVERSIDAD DE IBAGUE | D261: Académica | E261: Lab. Electrónica General (L1) | F261: 46023 | G261: =IFERROR(VLOOKUP(D261,Listas!$A$2:$B$20,2,FALSE()),999) -> 1 | H261: =IF(F261="","Sin fecha",IF(TODAY()-F261>180,"Revisar",IF(TODAY()-F261>90,"Próximo","Vigente"))) -> Revisar | J261: 120 | K261: 120 | L261: 41090 | M261: S
A262: U15200501068 | B262: TRANSMISOR DE PH | C262: MAQUINARIA Y EQUIPO MINI TRASMISOR DE PH MARCA NEWPORT MODELO PHTM-1. PROVEEDOR:890704382 UNIVERSIDAD DE IBAGUE | D262: Académica | E262: Lab. Electrónica General (L1) | F262: 46023 | G262: =IFERROR(VLOOKUP(D262,Listas!$A$2:$B$20,2,FALSE()),999) -> 1 | H262: =IF(F262="","Sin fecha",IF(TODAY()-F262>180,"Revisar",IF(TODAY()-F262>90,"Próximo","Vigente"))) -> Revisar | J262: 120 | K262: 120 | L262: 41090 | M262: S
A263: U15200501069 | B263: TRANSMISOR DE PH | C263: MAQUINARIA Y EQUIPO MINI TRASMISOR DE PH MARCA NEWPORT MODELO PHTM-1. PROVEEDOR:890704382 UNIVERSIDAD DE IBAGUE | D263: Académica | E263: Lab. Electrónica General (L1) | F263: 46023 | G263: =IFERROR(VLOOKUP(D263,Listas!$A$2:$B$20,2,FALSE()),999) -> 1 | H263: =IF(F263="","Sin fecha",IF(TODAY()-F263>180,"Revisar",IF(TODAY()-F263>90,"Próximo","Vigente"))) -> Revisar | J263: 120 | K263: 120 | L263: 41090 | M263: S
A264: U15201000996 | B264: VARIAC | C264: TRANSFORMADOR - VARIABLE TRANFORMER 140V 10A | D264: Académica | E264: Lab. Electrónica General (L1) | F264: 45809 | G264: =IFERROR(VLOOKUP(D264,Listas!$A$2:$B$20,2,FALSE()),999) -> 1 | H264: =IF(F264="","Sin fecha",IF(TODAY()-F264>180,"Revisar",IF(TODAY()-F264>90,"Próximo","Vigente"))) -> Revisar | J264: 120 | K264: 101 | L264: 43216 | M264: N
A265: U15201000997 | B265: VARIAC | C265: TRANSFORMADOR - VARIABLE TRANFORMER 140V 10A | D265: Académica | E265: Lab. Electrónica General (L1) | F265: 45809 | G265: =IFERROR(VLOOKUP(D265,Listas!$A$2:$B$20,2,FALSE()),999) -> 1 | H265: =IF(F265="","Sin fecha",IF(TODAY()-F265>180,"Revisar",IF(TODAY()-F265>90,"Próximo","Vigente"))) -> Revisar | J265: 120 | K265: 101 | L265: 43216 | M265: N
A266: U15201001072 | B266: VARIAC | C266: TRANSFORMADOR - TRANSFORMADOR VARIABLE 140V 10A MARCA: STACO MODELO: 3PN1010B - TIPO DE SALIDA: RECEPTÁCULO. VOLTAGE DE SALIDA: 140VAC SUMINISTRO DE VOLTAGE: 120VAC TIPO DE ENTRADA: ENCHUFE, CABLE DE 1.8 M CARGA MÁXIMA DE CORRIENTE CONSTANTE: 10A (1.4KVA) TAMAÑO: 176.78MM X 117.35MM X 139.70MM | D266: Académica | E266: Lab. Electrónica General (L1) | F266: 45809 | G266: =IFERROR(VLOOKUP(D266,Listas!$A$2:$B$20,2,FALSE()),999) -> 1 | H266: =IF(F266="","Sin fecha",IF(TODAY()-F266>180,"Revisar",IF(TODAY()-F266>90,"Próximo","Vigente"))) -> Revisar | J266: 120 | K266: 93 | L266: 43441 | M266: N
A267: U15201001073 | B267: VARIAC | C267: TRANSFORMADOR - TRANSFORMADOR VARIABLE 140V 10A MARCA: STACO MODELO: 3PN1010B - TIPO DE SALIDA: RECEPTÁCULO. VOLTAGE DE SALIDA: 140VAC SUMINISTRO DE VOLTAGE: 120VAC TIPO DE ENTRADA: ENCHUFE, CABLE DE 1.8 M CARGA MÁXIMA DE CORRIENTE CONSTANTE: 10A (1.4KVA) TAMAÑO: 176.78MM X 117.35MM X 139.70MM | D267: Académica | E267: Lab. Electrónica General (L1) | F267: 45809 | G267: =IFERROR(VLOOKUP(D267,Listas!$A$2:$B$20,2,FALSE()),999) -> 1 | H267: =IF(F267="","Sin fecha",IF(TODAY()-F267>180,"Revisar",IF(TODAY()-F267>90,"Próximo","Vigente"))) -> Revisar | J267: 120 | K267: 93 | L267: 43459 | M267: N
A268: U15200500960 | B268: VARIADOR | C268: MAQUINARIA Y EQUIPO VARIADOR DE VELOCIDAD . PROVEEDOR:890704382 UNIVERSIDAD DE IBAGUE | D268: Académica | E268: Lab. Electrónica General (L1) | F268: 45809 | G268: =IFERROR(VLOOKUP(D268,Listas!$A$2:$B$20,2,FALSE()),999) -> 1 | H268: =IF(F268="","Sin fecha",IF(TODAY()-F268>180,"Revisar",IF(TODAY()-F268>90,"Próximo","Vigente"))) -> Revisar | J268: 120 | K268: 120 | L268: 41090 | M268: S
A269: U15200500961 | B269: VARIADOR | C269: MAQUINARIA Y EQUIPO VARIADOR DE VELOCIDAD . PROVEEDOR:890704382 UNIVERSIDAD DE IBAGUE | D269: Académica | E269: Lab. Electrónica General (L1) | F269: 45809 | G269: =IFERROR(VLOOKUP(D269,Listas!$A$2:$B$20,2,FALSE()),999) -> 1 | H269: =IF(F269="","Sin fecha",IF(TODAY()-F269>180,"Revisar",IF(TODAY()-F269>90,"Próximo","Vigente"))) -> Revisar | J269: 1 | K269: 1 | L269: 42886 | M269: S
A270: U15200500962 | B270: VARIADOR | C270: MAQUINARIA Y EQUIPO VARIADOR DE VELOCIDAD . PROVEEDOR:890704382 UNIVERSIDAD DE IBAGUE | D270: Académica | E270: Lab. Electrónica General (L1) | F270: 45809 | G270: =IFERROR(VLOOKUP(D270,Listas!$A$2:$B$20,2,FALSE()),999) -> 1 | H270: =IF(F270="","Sin fecha",IF(TODAY()-F270>180,"Revisar",IF(TODAY()-F270>90,"Próximo","Vigente"))) -> Revisar | J270: 120 | K270: 120 | L270: 41090 | M270: S
A271: U15200501058 | B271: VARIADOR | C271: MAQUINARIA Y EQUIPO VARIADOR DE VELOCIDAD MARCA YASKAWA. PROVEEDOR:890704382 UNIVERSIDAD DE IBAGUE | D271: Académica | E271: Lab. Electrónica General (L1) | F271: 45809 | G271: =IFERROR(VLOOKUP(D271,Listas!$A$2:$B$20,2,FALSE()),999) -> 1 | H271: =IF(F271="","Sin fecha",IF(TODAY()-F271>180,"Revisar",IF(TODAY()-F271>90,"Próximo","Vigente"))) -> Revisar | J271: 120 | K271: 120 | L271: 41090 | M271: S
... A288: U15200500136 | B288: MULTIMETRO | C288: MAQUINARIA Y EQUIPO MULTIMETRO MARCA UNI-T COLOR NEGRO Y ROJO MODELO UT39C. PROVEEDOR:890704382 UNIVERSIDAD DE IBAGUE | D288: Académica | E288: Lab. Investiación 1 | F288: 45962 | G288: =IFERROR(VLOOKUP(D288,Listas!$A$2:$B$20,2,FALSE()),999) -> 1 | H288: =IF(F288="","Sin fecha",IF(TODAY()-F288>180,"Revisar",IF(TODAY()-F288>90,"Próximo","Vigente"))) -> Revisar | J288: 120 | K288: 120 | L288: 41090 | M288: S
A289: U15201000731 | B289: MULTIMETRO | C289: MULTIMETRO - DIGITAL FLUKE DE PRECISÓN | D289: Académica | E289: Lab. Investiación 1 | G289: =IFERROR(VLOOKUP(D289,Listas!$A$2:$B$20,2,FALSE()),999) -> 1 | H289: =IF(F289="","Sin fecha",IF(TODAY()-F289>180,"Revisar",IF(TODAY()-F289>90,"Próximo","Vigente"))) -> Sin fecha | J289: 120 | K289: 108 | L289: 42987 | M289: N
A290: U15200501310 | B290: OSCILOSCOPIO | C290: MAQUINARIA Y EQUIPO OSCILOSCOPIO DIGITAL . PROVEEDOR:890704382 UNIVERSIDAD DE IBAGUE | D290: Académica | E290: Lab. Investiación 1 | F290: 45962 | G290: =IFERROR(VLOOKUP(D290,Listas!$A$2:$B$20,2,FALSE()),999) -> 1 | H290: =IF(F290="","Sin fecha",IF(TODAY()-F290>180,"Revisar",IF(TODAY()-F290>90,"Próximo","Vigente"))) -> Revisar | J290: 120 | K290: 120 | L290: 41090 | M290: S
A291: U15200501311 | B291: OSCILOSCOPIO | C291: MAQUINARIA Y EQUIPO OSCILOSCOPIO DIGITAL . PROVEEDOR:890704382 UNIVERSIDAD DE IBAGUE | D291: Académica | E291: Lab. Investiación 1 | F291: 45962 | G291: =IFERROR(VLOOKUP(D291,Listas!$A$2:$B$20,2,FALSE()),999) -> 1 | H291: =IF(F291="","Sin fecha",IF(TODAY()-F291>180,"Revisar",IF(TODAY()-F291>90,"Próximo","Vigente"))) -> Revisar | J291: 120 | K291: 120 | L291: 41090 | M291: S
A292: U15201000456 | B292: OSCILOSCOPIO | C292: EQUIPO LABORATORIO OSCILOSCOPIO DIGITAL GROTTEN. PROVEEDOR:890704382 UNIVERSIDAD DE IBAGUE | D292: Académica | E292: Lab. Investiación 1 | F292: 45962 | G292: =IFERROR(VLOOKUP(D292,Listas!$A$2:$B$20,2,FALSE()),999) -> 1 | H292: =IF(F292="","Sin fecha",IF(TODAY()-F292>180,"Revisar",IF(TODAY()-F292>90,"Próximo","Vigente"))) -> Revisar | J292: 120 | K292: 120 | L292: 41090 | M292: S
A293: U15201000457 | B293: OSCILOSCOPIO | C293: EQUIPO LABORATORIO OSCILOSCOPIO DIGITAL . PROVEEDOR:890704382 UNIVERSIDAD DE IBAGUE | D293: Académica | E293: Lab. Investiación 1 | F293: 45962 | G293: =IFERROR(VLOOKUP(D293,Listas!$A$2:$B$20,2,FALSE()),999) -> 1 | H293: =IF(F293="","Sin fecha",IF(TODAY()-F293>180,"Revisar",IF(TODAY()-F293>90,"Próximo","Vigente"))) -> Revisar | J293: 120 | K293: 120 | L293: 41090 | M293: S
A294: U15201000458 | B294: OSCILOSCOPIO | C294: EQUIPO LABORATORIO OSCILOSCOPIO DIGITAL . PROVEEDOR:890704382 UNIVERSIDAD DE IBAGUE | D294: Académica | E294: Lab. Investiación 1 | F294: 45809 | G294: =IFERROR(VLOOKUP(D294,Listas!$A$2:$B$20,2,FALSE()),999) -> 1 | H294: =IF(F294="","Sin fecha",IF(TODAY()-F294>180,"Revisar",IF(TODAY()-F294>90,"Próximo","Vigente"))) -> Revisar | J294: 120 | K294: 120 | L294: 42643 | M294: S
A295: U15201000727 | B295: OSCILOSCOPIO | C295: OSCILOSCOPIO - OSCILOSCOPIO DIGITAL CON ¿CARACTERÍSTICAS 4 CANALES | D295: Académica | E295: Lab. Investiación 1 | F295: 45809 | G295: =IFERROR(VLOOKUP(D295,Listas!$A$2:$B$20,2,FALSE()),999) -> 1 | H295: =IF(F295="","Sin fecha",IF(TODAY()-F295>180,"Revisar",IF(TODAY()-F295>90,"Próximo","Vigente"))) -> Revisar | J295: 120 | K295: 109 | L295: 42972 | M295: N
A296: U15201000728 | B296: OSCILOSCOPIO | C296: OSCILOSCOPIO - OSCILOSCOPIO DIGITAL CON ¿CARACTERÍSTICAS 4 CANALES | D296: Académica | E296: Lab. Investiación 1 | F296: 45809 | G296: =IFERROR(VLOOKUP(D296,Listas!$A$2:$B$20,2,FALSE()),999) -> 1 | H296: =IF(F296="","Sin fecha",IF(TODAY()-F296>180,"Revisar",IF(TODAY()-F296>90,"Próximo","Vigente"))) -> Revisar | J296: 120 | K296: 109 | L296: 42972 | M296: N
A297: U15200500867 | B297: PINZA AISLADA | C297: MAQUINARIA Y EQUIPO PINZA AISLADA DE CORRIENTE . PROVEEDOR:890704382 UNIVERSIDAD DE IBAGUE | D297: Académica | E297: Lab. Investiación 1 | F297: 45809 | G297: =IFERROR(VLOOKUP(D297,Listas!$A$2:$B$20,2,FALSE()),999) -> 1 | H297: =IF(F297="","Sin fecha",IF(TODAY()-F297>180,"Revisar",IF(TODAY()-F297>90,"Próximo","Vigente"))) -> Revisar | J297: 120 | K297: 120 | L297: 42247 | M297: S
A298: U15200500872 | B298: PROBADOR DE CORRIENTE | C298: MAQUINARIA Y EQUIPO PUNTA DE CORRIENTE . PROVEEDOR:890704382 UNIVERSIDAD DE IBAGUE | D298: Académica | E298: Lab. Investiación 1 | F298: 45962 | G298: =IFERROR(VLOOKUP(D298,Listas!$A$2:$B$20,2,FALSE()),999) -> 1 | H298: =IF(F298="","Sin fecha",IF(TODAY()-F298>180,"Revisar",IF(TODAY()-F298>90,"Próximo","Vigente"))) -> Revisar | J298: 120 | K298: 120 | L298: 41090 | M298: S
A299: U15200500883 | B299: PROBADOR DE CORRIENTE | C299: MAQUINARIA Y EQUIPO PUNTA MEDIDOR DE CORRIENTE . PROVEEDOR:890704382 UNIVERSIDAD DE IBAGUE | D299: Académica | E299: Lab. Investiación 1 | F299: 45809 | G299: =IFERROR(VLOOKUP(D299,Listas!$A$2:$B$20,2,FALSE()),999) -> 1 | H299: =IF(F299="","Sin fecha",IF(TODAY()-F299>180,"Revisar",IF(TODAY()-F299>90,"Próximo","Vigente"))) -> Revisar | J299: 120 | K299: 120 | L299: 39263 | M299: S
A300: U15200500878 | B300: REOSTATO | C300: MAQUINARIA Y EQUIPO RESISTENCIA VARIABLE . PROVEEDOR:890704382 UNIVERSIDAD DE IBAGUE | D300: Académica | E300: Lab. Investiación 1 | F300: 45962 | G300: =IFERROR(VLOOKUP(D300,Listas!$A$2:$B$20,2,FALSE()),999) -> 1 | H300: =IF(F300="","Sin fecha",IF(TODAY()-F300>180,"Revisar",IF(TODAY()-F300>90,"Próximo","Vigente"))) -> Revisar | J300: 120 | K300: 120 | L300: 41090 | M300: S
A301: U15200500879 | B301: REOSTATO | C301: MAQUINARIA Y EQUIPO RESISTENCIA VARIABLE . PROVEEDOR:890704382 UNIVERSIDAD DE IBAGUE | D301: Académica | E301: Lab. Investiación 1 | F301: 45962 | G301: =IFERROR(VLOOKUP(D301,Listas!$A$2:$B$20,2,FALSE()),999) -> 1 | H301: =IF(F301="","Sin fecha",IF(TODAY()-F301>180,"Revisar",IF(TODAY()-F301>90,"Próximo","Vigente"))) -> Revisar | J301: 120 | K301: 120 | L301: 41090 | M301: S
...

Sheet Listas
A1: Área | B1: Orden | D1: Dependencia
A2: Académica | B2: 1 | D2: CIPAV
A3: Administrativa | B3: 2 | D3: Energías renovables
A4: Tecnología | B4: 3 | D4: L6
A5: Servicios Generales | B5: 4 | D5: Lab. de Diseño de Sistemas Mecanicos
A6: Financiera | B6: 5 | D6: Lab. de Diseño Mecatronico
A7: Bienestar Universitario | B7: 6 | D7: Lab. Electromedicina L4
A8: Investigación | B8: 7 | D8: Lab. Electrónica General (L1)
A9: Extensión | B9: 8 | D9: Lab. Investiación 1
D10: Lab. Investigación 1
D11: Lab. Investigación 2
D12: Lab. Software Espec. L6
D13: Lab. Telecomunicaciones
D14: Laboratori Fisica Electricidad y Magnetismo
D15: Laboratorio Analisís químico
D16: LABORATORIO DE BIOLOGÍA
D17: LABORATORIO DE BIOLOGÍA MOLECULAR
D18: Laboratorio de combustión
D19: Laboratorio de Metalografía y Tratamientos Termicos
D20: LABORATORIO DE MICROBIOLOGÍA AMBIENTAL
D21: LABORATORIO DE SUELOS, PAVIMENTOS Y CONCRETOS 1
... D29: Redes Computacionales o LM3
